nonebot_plugin_diffsinger/__init__.py
nonebot_plugin_diffsinger/config.py
nonebot_plugin_diffsinger/data_source.py
nonebot_plugin_diffsinger-0.1.13.dist-info/WHEEL
nonebot_plugin_diffsinger-0.1.13.dist-info/METADATA
nonebot_plugin_diffsinger-0.1.13.dist-info/licenses/LICENSE
nonebot_plugin_diffsinger-0.1.13.dist-info/RECORD
