Metadata-Version: 2.1
Name: nonebot-plugin-diffsinger
Version: 0.1.13
Summary: 用DiffSinger让bot唱歌
License: MIT
Author-email: zhzhongshi <zhz894524@163.com>
Requires-Python: >=3.8
Requires-Dist: httpx
Requires-Dist: librosa
Requires-Dist: nonebot-adapter-onebot
Requires-Dist: nonebot2<3.0.0,>=2.2.0
Project-URL: Homepage, https://github.com/zhzhongshi/nonebot-plugin-diffsinger
Project-URL: Repository, https://github.com/zhzhongshi/nonebot-plugin-diffsinger
